{"cameraMode":{"drawMode":0,"name":"Shaded","section":"Shading Mode"},"sceneLighting":true,"audioPlay":false,"sceneViewState":{"m_AlwaysRefresh":false,"showFog":true,"showSkybox":true,"showFlares":true,"showImageEffects":true,"showParticleSystems":true,"showVisualEffectGraphs":true,"m_FxEnabled":true},"in2DMode":false,"pivot":{"x":-63.1313362121582,"y":89.45244598388672,"z":228.80630493164063},"rotation":{"x":0.2986680865287781,"y":0.6899319887161255,"z":-0.38483479619026186,"w":0.5354561805725098},"size":274.0794982910156,"orthographic":true}